{
  "modelVersion" : "2.2",
  "id" : "technicalInterviewListForm",
  "name" : "technicalInterviewListForm",
  "lastUpdate" : 1640637465567,
  "rows" : [
    [
      {
        "type" : "container",
        "dimension" : {
          "xs" : 12
        },
        "propertyValues" : { },
        "reference" : "bab0f442-b42b-4fb0-8d24-f03163ed12c3",
        "hasValidationError" : false,
        "id" : "pbContainer",
        "rows" : [
          [
            {
              "type" : "component",
              "dimension" : {
                "md" : 12,
                "sm" : 12,
                "xs" : 12,
                "lg" : 12
              },
              "propertyValues" : {
                "hidden" : {
                  "type" : "constant",
                  "value" : false
                },
                "level" : {
                  "type" : "constant",
                  "value" : "Level 1"
                },
                "cssClasses" : {
                  "type" : "constant",
                  "value" : ""
                },
                "text" : {
                  "type" : "interpolation",
                  "value" : "{{ task.displayName }}"
                },
                "alignment" : {
                  "type" : "constant",
                  "value" : "center"
                },
                "dimension" : {
                  "type" : "constant",
                  "value" : 12
                }
              },
              "reference" : "33493e8b-577a-4c0b-82c4-76b612120792",
              "hasValidationError" : false,
              "id" : "pbTitle",
              "description" : ""
            }
          ],
          [
            {
              "type" : "component",
              "dimension" : {
                "md" : 12,
                "sm" : 12,
                "xs" : 12,
                "lg" : 12
              },
              "propertyValues" : {
                "allowHtml" : {
                  "type" : "constant",
                  "value" : true
                },
                "labelHidden" : {
                  "type" : "constant",
                  "value" : true
                },
                "hidden" : {
                  "type" : "constant",
                  "value" : false
                },
                "cssClasses" : {
                  "type" : "constant",
                  "value" : ""
                },
                "label" : {
                  "type" : "interpolation"
                },
                "text" : {
                  "type" : "interpolation",
                  "value" : "{{ task.displayDescription }}"
                },
                "alignment" : {
                  "type" : "constant",
                  "value" : "left"
                },
                "dimension" : {
                  "type" : "constant",
                  "value" : 12
                }
              },
              "reference" : "d0e89705-a8d0-400f-b036-d3c4552e4383",
              "hasValidationError" : false,
              "id" : "pbText",
              "description" : ""
            }
          ]
        ]
      }
    ],
    [
      {
        "type" : "formContainer",
        "dimension" : {
          "xs" : 12
        },
        "propertyValues" : { },
        "reference" : "605b903d-be03-48b5-8903-2a6f9e3d39aa",
        "hasValidationError" : false,
        "id" : "pbFormContainer",
        "container" : {
          "type" : "container",
          "dimension" : {
            "xs" : 12
          },
          "propertyValues" : { },
          "reference" : "b17ef1ac-47ce-4b2b-96f4-8829472ab88c",
          "hasValidationError" : false,
          "id" : "pbContainer",
          "rows" : [
            [
              {
                "type" : "component",
                "dimension" : {
                  "md" : 12,
                  "sm" : 12,
                  "xs" : 12,
                  "lg" : 12
                },
                "propertyValues" : {
                  "hidden" : {
                    "type" : "constant",
                    "value" : false
                  },
                  "level" : {
                    "type" : "constant",
                    "value" : "Level 4"
                  },
                  "cssClasses" : {
                    "type" : "constant",
                    "value" : ""
                  },
                  "text" : {
                    "type" : "interpolation",
                    "value" : "Job Application"
                  },
                  "alignment" : {
                    "type" : "constant",
                    "value" : "left"
                  },
                  "dimension" : {
                    "type" : "constant",
                    "value" : 12
                  }
                },
                "reference" : "4238fa15-c27b-4549-8229-36409a816f9c",
                "hasValidationError" : false,
                "id" : "pbTitle",
                "description" : ""
              }
            ],
            [
              {
                "type" : "container",
                "dimension" : {
                  "md" : 12,
                  "sm" : 12,
                  "xs" : 12,
                  "lg" : 12
                },
                "propertyValues" : {
                  "repeatedCollection" : {
                    "type" : "variable"
                  },
                  "hidden" : {
                    "type" : "constant",
                    "value" : false
                  },
                  "cssClasses" : {
                    "type" : "constant",
                    "value" : ""
                  },
                  "dimension" : {
                    "type" : "constant",
                    "value" : 12
                  }
                },
                "reference" : "c73314bb-f224-4410-86c3-1b9e539ef86a",
                "hasValidationError" : false,
                "id" : "pbContainer",
                "rows" : [
                  [
                    {
                      "type" : "component",
                      "dimension" : {
                        "md" : 12,
                        "sm" : 12,
                        "xs" : 12,
                        "lg" : 12
                      },
                      "propertyValues" : {
                        "labelHidden" : {
                          "type" : "constant",
                          "value" : false
                        },
                        "hidden" : {
                          "type" : "constant",
                          "value" : false
                        },
                        "labelPosition" : {
                          "type" : "constant",
                          "value" : "top"
                        },
                        "cssClasses" : {
                          "type" : "constant",
                          "value" : ""
                        },
                        "labelWidth" : {
                          "type" : "constant",
                          "value" : 1
                        },
                        "readOnly" : {
                          "type" : "constant",
                          "value" : true
                        },
                        "label" : {
                          "type" : "interpolation",
                          "value" : "Name"
                        },
                        "placeholder" : {
                          "type" : "constant"
                        },
                        "type" : {
                          "type" : "constant",
                          "value" : "text"
                        },
                        "dimension" : {
                          "type" : "constant",
                          "value" : 12
                        },
                        "value" : {
                          "type" : "variable",
                          "value" : "jobApplication.name"
                        },
                        "required" : {
                          "type" : "constant",
                          "value" : false
                        },
                        "minLength" : {
                          "type" : "constant",
                          "value" : ""
                        },
                        "maxLength" : {
                          "type" : "constant",
                          "value" : ""
                        },
                        "min" : {
                          "type" : "constant"
                        },
                        "max" : {
                          "type" : "constant"
                        },
                        "step" : {
                          "type" : "constant",
                          "value" : 1
                        }
                      },
                      "reference" : "28d00f0d-105a-4ee1-bda3-3cc54973210a",
                      "hasValidationError" : false,
                      "id" : "pbInput",
                      "description" : ""
                    }
                  ],
                  [
                    {
                      "type" : "component",
                      "dimension" : {
                        "md" : 12,
                        "sm" : 12,
                        "xs" : 12,
                        "lg" : 12
                      },
                      "propertyValues" : {
                        "labelHidden" : {
                          "type" : "constant",
                          "value" : false
                        },
                        "hidden" : {
                          "type" : "constant",
                          "value" : false
                        },
                        "labelPosition" : {
                          "type" : "constant",
                          "value" : "top"
                        },
                        "cssClasses" : {
                          "type" : "constant",
                          "value" : ""
                        },
                        "labelWidth" : {
                          "type" : "constant",
                          "value" : 1
                        },
                        "readOnly" : {
                          "type" : "constant",
                          "value" : true
                        },
                        "label" : {
                          "type" : "interpolation",
                          "value" : "Surname"
                        },
                        "placeholder" : {
                          "type" : "constant"
                        },
                        "type" : {
                          "type" : "constant",
                          "value" : "text"
                        },
                        "dimension" : {
                          "type" : "constant",
                          "value" : 12
                        },
                        "value" : {
                          "type" : "variable",
                          "value" : "jobApplication.surname"
                        },
                        "required" : {
                          "type" : "constant",
                          "value" : false
                        },
                        "minLength" : {
                          "type" : "constant",
                          "value" : ""
                        },
                        "maxLength" : {
                          "type" : "constant",
                          "value" : ""
                        },
                        "min" : {
                          "type" : "constant"
                        },
                        "max" : {
                          "type" : "constant"
                        },
                        "step" : {
                          "type" : "constant",
                          "value" : 1
                        }
                      },
                      "reference" : "c50fc7e4-cd4e-4d82-ad8f-bcf597cb645e",
                      "hasValidationError" : false,
                      "id" : "pbInput",
                      "description" : ""
                    }
                  ],
                  [
                    {
                      "type" : "component",
                      "dimension" : {
                        "md" : 12,
                        "sm" : 12,
                        "xs" : 12,
                        "lg" : 12
                      },
                      "propertyValues" : {
                        "labelHidden" : {
                          "type" : "constant",
                          "value" : false
                        },
                        "hidden" : {
                          "type" : "constant",
                          "value" : false
                        },
                        "labelPosition" : {
                          "type" : "constant",
                          "value" : "top"
                        },
                        "cssClasses" : {
                          "type" : "constant",
                          "value" : ""
                        },
                        "labelWidth" : {
                          "type" : "constant",
                          "value" : 1
                        },
                        "readOnly" : {
                          "type" : "constant",
                          "value" : true
                        },
                        "label" : {
                          "type" : "interpolation",
                          "value" : "Email"
                        },
                        "placeholder" : {
                          "type" : "constant"
                        },
                        "type" : {
                          "type" : "constant",
                          "value" : "text"
                        },
                        "dimension" : {
                          "type" : "constant",
                          "value" : 12
                        },
                        "value" : {
                          "type" : "variable",
                          "value" : "jobApplication.email"
                        },
                        "required" : {
                          "type" : "constant",
                          "value" : false
                        },
                        "minLength" : {
                          "type" : "constant",
                          "value" : ""
                        },
                        "maxLength" : {
                          "type" : "constant",
                          "value" : ""
                        },
                        "min" : {
                          "type" : "constant"
                        },
                        "max" : {
                          "type" : "constant"
                        },
                        "step" : {
                          "type" : "constant",
                          "value" : 1
                        }
                      },
                      "reference" : "4f668071-47a5-4e9c-b3b3-4638832e5304",
                      "hasValidationError" : false,
                      "id" : "pbInput",
                      "description" : ""
                    }
                  ],
                  [
                    {
                      "type" : "component",
                      "dimension" : {
                        "md" : 12,
                        "sm" : 12,
                        "xs" : 12,
                        "lg" : 12
                      },
                      "propertyValues" : {
                        "labelHidden" : {
                          "type" : "constant",
                          "value" : false
                        },
                        "hidden" : {
                          "type" : "constant",
                          "value" : false
                        },
                        "labelPosition" : {
                          "type" : "constant",
                          "value" : "top"
                        },
                        "cssClasses" : {
                          "type" : "constant",
                          "value" : ""
                        },
                        "labelWidth" : {
                          "type" : "constant",
                          "value" : 1
                        },
                        "readOnly" : {
                          "type" : "constant",
                          "value" : true
                        },
                        "label" : {
                          "type" : "interpolation",
                          "value" : "Address"
                        },
                        "placeholder" : {
                          "type" : "constant"
                        },
                        "type" : {
                          "type" : "constant",
                          "value" : "text"
                        },
                        "dimension" : {
                          "type" : "constant",
                          "value" : 12
                        },
                        "value" : {
                          "type" : "variable",
                          "value" : "jobApplication.address"
                        },
                        "required" : {
                          "type" : "constant",
                          "value" : false
                        },
                        "minLength" : {
                          "type" : "constant",
                          "value" : ""
                        },
                        "maxLength" : {
                          "type" : "constant",
                          "value" : ""
                        },
                        "min" : {
                          "type" : "constant"
                        },
                        "max" : {
                          "type" : "constant"
                        },
                        "step" : {
                          "type" : "constant",
                          "value" : 1
                        }
                      },
                      "reference" : "114241a4-df2d-4751-bbe5-1cbeba6c62d3",
                      "hasValidationError" : false,
                      "id" : "pbInput",
                      "description" : ""
                    }
                  ],
                  [
                    {
                      "type" : "component",
                      "dimension" : {
                        "md" : 12,
                        "sm" : 12,
                        "xs" : 12,
                        "lg" : 12
                      },
                      "propertyValues" : {
                        "labelHidden" : {
                          "type" : "constant",
                          "value" : false
                        },
                        "hidden" : {
                          "type" : "constant",
                          "value" : false
                        },
                        "labelPosition" : {
                          "type" : "constant",
                          "value" : "top"
                        },
                        "cssClasses" : {
                          "type" : "constant",
                          "value" : ""
                        },
                        "labelWidth" : {
                          "type" : "constant",
                          "value" : 1
                        },
                        "readOnly" : {
                          "type" : "constant",
                          "value" : true
                        },
                        "label" : {
                          "type" : "interpolation",
                          "value" : "Grade Of Education"
                        },
                        "placeholder" : {
                          "type" : "constant"
                        },
                        "type" : {
                          "type" : "constant",
                          "value" : "number"
                        },
                        "dimension" : {
                          "type" : "constant",
                          "value" : 12
                        },
                        "value" : {
                          "type" : "variable",
                          "value" : "jobApplication.gradeOfEducation"
                        },
                        "required" : {
                          "type" : "constant",
                          "value" : false
                        },
                        "minLength" : {
                          "type" : "constant",
                          "value" : ""
                        },
                        "maxLength" : {
                          "type" : "constant",
                          "value" : ""
                        },
                        "min" : {
                          "type" : "constant"
                        },
                        "max" : {
                          "type" : "constant"
                        },
                        "step" : {
                          "type" : "constant",
                          "value" : 1
                        }
                      },
                      "reference" : "f3417cd4-f247-4f91-870a-6d7de2ca3c5c",
                      "hasValidationError" : false,
                      "id" : "pbInput",
                      "description" : ""
                    }
                  ],
                  [
                    {
                      "type" : "component",
                      "dimension" : {
                        "md" : 12,
                        "sm" : 12,
                        "xs" : 12,
                        "lg" : 12
                      },
                      "propertyValues" : {
                        "labelHidden" : {
                          "type" : "constant",
                          "value" : false
                        },
                        "hidden" : {
                          "type" : "constant",
                          "value" : false
                        },
                        "labelPosition" : {
                          "type" : "constant",
                          "value" : "top"
                        },
                        "cssClasses" : {
                          "type" : "constant",
                          "value" : ""
                        },
                        "labelWidth" : {
                          "type" : "constant",
                          "value" : 1
                        },
                        "readOnly" : {
                          "type" : "constant",
                          "value" : true
                        },
                        "label" : {
                          "type" : "interpolation",
                          "value" : "Cv"
                        },
                        "placeholder" : {
                          "type" : "constant"
                        },
                        "type" : {
                          "type" : "constant",
                          "value" : "text"
                        },
                        "dimension" : {
                          "type" : "constant",
                          "value" : 12
                        },
                        "value" : {
                          "type" : "variable",
                          "value" : "jobApplication.cv"
                        },
                        "required" : {
                          "type" : "constant",
                          "value" : false
                        },
                        "minLength" : {
                          "type" : "constant",
                          "value" : ""
                        },
                        "maxLength" : {
                          "type" : "constant",
                          "value" : ""
                        },
                        "min" : {
                          "type" : "constant"
                        },
                        "max" : {
                          "type" : "constant"
                        },
                        "step" : {
                          "type" : "constant",
                          "value" : 1
                        }
                      },
                      "reference" : "9fe0c48d-ce50-4c53-a81b-07b4396b4dcb",
                      "hasValidationError" : false,
                      "id" : "pbInput",
                      "description" : ""
                    }
                  ],
                  [
                    {
                      "type" : "component",
                      "dimension" : {
                        "md" : 12,
                        "sm" : 12,
                        "xs" : 12,
                        "lg" : 12
                      },
                      "propertyValues" : {
                        "labelHidden" : {
                          "type" : "constant",
                          "value" : false
                        },
                        "hidden" : {
                          "type" : "constant",
                          "value" : false
                        },
                        "labelPosition" : {
                          "type" : "constant",
                          "value" : "top"
                        },
                        "cssClasses" : {
                          "type" : "constant",
                          "value" : ""
                        },
                        "labelWidth" : {
                          "type" : "constant",
                          "value" : 1
                        },
                        "readOnly" : {
                          "type" : "constant",
                          "value" : true
                        },
                        "label" : {
                          "type" : "interpolation",
                          "value" : "Letter"
                        },
                        "placeholder" : {
                          "type" : "constant"
                        },
                        "type" : {
                          "type" : "constant",
                          "value" : "text"
                        },
                        "dimension" : {
                          "type" : "constant",
                          "value" : 12
                        },
                        "value" : {
                          "type" : "variable",
                          "value" : "jobApplication.letter"
                        },
                        "required" : {
                          "type" : "constant",
                          "value" : false
                        },
                        "minLength" : {
                          "type" : "constant",
                          "value" : ""
                        },
                        "maxLength" : {
                          "type" : "constant",
                          "value" : ""
                        },
                        "min" : {
                          "type" : "constant"
                        },
                        "max" : {
                          "type" : "constant"
                        },
                        "step" : {
                          "type" : "constant",
                          "value" : 1
                        }
                      },
                      "reference" : "04f74648-e75a-41ce-9c4b-c0fb60cdacc3",
                      "hasValidationError" : false,
                      "id" : "pbInput",
                      "description" : ""
                    }
                  ],
                  [
                    {
                      "type" : "component",
                      "dimension" : {
                        "md" : 12,
                        "sm" : 12,
                        "xs" : 12,
                        "lg" : 12
                      },
                      "propertyValues" : {
                        "hidden" : {
                          "type" : "constant",
                          "value" : false
                        },
                        "level" : {
                          "type" : "constant",
                          "value" : "Level 4"
                        },
                        "cssClasses" : {
                          "type" : "constant",
                          "value" : ""
                        },
                        "text" : {
                          "type" : "interpolation",
                          "value" : "Choosen Interview Term"
                        },
                        "alignment" : {
                          "type" : "constant",
                          "value" : "left"
                        },
                        "dimension" : {
                          "type" : "constant",
                          "value" : 12
                        }
                      },
                      "reference" : "8ca6f3ff-794a-4bdf-a579-1491c16395a8",
                      "hasValidationError" : false,
                      "id" : "pbTitle",
                      "description" : ""
                    }
                  ],
                  [
                    {
                      "type" : "container",
                      "dimension" : {
                        "md" : 12,
                        "sm" : 12,
                        "xs" : 12,
                        "lg" : 12
                      },
                      "propertyValues" : {
                        "repeatedCollection" : {
                          "type" : "variable"
                        },
                        "hidden" : {
                          "type" : "constant",
                          "value" : false
                        },
                        "cssClasses" : {
                          "type" : "constant",
                          "value" : ""
                        },
                        "dimension" : {
                          "type" : "constant",
                          "value" : 12
                        }
                      },
                      "reference" : "1809d738-cc34-41d6-9aac-77f013c6f4f2",
                      "hasValidationError" : false,
                      "id" : "pbContainer",
                      "rows" : [
                        [
                          {
                            "type" : "component",
                            "dimension" : {
                              "md" : 12,
                              "sm" : 12,
                              "xs" : 12,
                              "lg" : 12
                            },
                            "propertyValues" : {
                              "showNow" : {
                                "type" : "constant",
                                "value" : true
                              },
                              "hidden" : {
                                "type" : "constant",
                                "value" : false
                              },
                              "inlineInput" : {
                                "type" : "constant",
                                "value" : true
                              },
                              "dateFormat" : {
                                "type" : "constant",
                                "value" : "MM/dd/yyyy"
                              },
                              "cssClasses" : {
                                "type" : "constant",
                                "value" : ""
                              },
                              "labelWidth" : {
                                "type" : "constant",
                                "value" : 1
                              },
                              "readOnly" : {
                                "type" : "constant",
                                "value" : true
                              },
                              "label" : {
                                "type" : "interpolation",
                                "value" : "Date Time"
                              },
                              "type" : {
                                "type" : "constant"
                              },
                              "required" : {
                                "type" : "constant",
                                "value" : false
                              },
                              "todayLabel" : {
                                "type" : "constant",
                                "value" : "Today"
                              },
                              "timePlaceholder" : {
                                "type" : "constant",
                                "value" : "Enter a time (h:mm:ss a)"
                              },
                              "labelHidden" : {
                                "type" : "constant",
                                "value" : false
                              },
                              "showToday" : {
                                "type" : "constant",
                                "value" : true
                              },
                              "labelPosition" : {
                                "type" : "constant",
                                "value" : "top"
                              },
                              "timeFormat" : {
                                "type" : "constant",
                                "value" : "h:mm:ss a"
                              },
                              "placeholder" : {
                                "type" : "constant",
                                "value" : "Enter a date (mm/dd/yyyy)"
                              },
                              "nowLabel" : {
                                "type" : "constant",
                                "value" : "Now"
                              },
                              "dimension" : {
                                "type" : "constant",
                                "value" : 12
                              },
                              "value" : {
                                "type" : "variable",
                                "value" : "jobApplication_choosenInterviewTerm.dateTime"
                              },
                              "withTimeZone" : {
                                "type" : "constant",
                                "value" : false
                              }
                            },
                            "reference" : "d0fbfb7c-37e0-4691-a086-4b0f97a83d72",
                            "hasValidationError" : false,
                            "id" : "pbDateTimePicker",
                            "description" : ""
                          }
                        ]
                      ]
                    }
                  ]
                ]
              }
            ],
            [
              {
                "type" : "component",
                "dimension" : {
                  "md" : 12,
                  "sm" : 12,
                  "xs" : 12,
                  "lg" : 12
                },
                "propertyValues" : {
                  "hidden" : {
                    "type" : "constant",
                    "value" : false
                  },
                  "level" : {
                    "type" : "constant",
                    "value" : "Level 4"
                  },
                  "cssClasses" : {
                    "type" : "constant",
                    "value" : ""
                  },
                  "text" : {
                    "type" : "interpolation",
                    "value" : "Interview Result"
                  },
                  "alignment" : {
                    "type" : "constant",
                    "value" : "left"
                  },
                  "dimension" : {
                    "type" : "constant",
                    "value" : 12
                  }
                },
                "reference" : "34e64d4f-4a60-423b-8cc6-043d9fadb8d0",
                "hasValidationError" : false,
                "id" : "pbTitle",
                "description" : ""
              }
            ],
            [
              {
                "type" : "container",
                "dimension" : {
                  "md" : 12,
                  "sm" : 12,
                  "xs" : 12,
                  "lg" : 12
                },
                "propertyValues" : {
                  "repeatedCollection" : {
                    "type" : "variable",
                    "value" : "interviewResults"
                  },
                  "hidden" : {
                    "type" : "constant",
                    "value" : false
                  },
                  "cssClasses" : {
                    "type" : "constant",
                    "value" : ""
                  },
                  "dimension" : {
                    "type" : "constant",
                    "value" : 12
                  }
                },
                "reference" : "067944b5-0334-47cf-8416-a1249632a5b2",
                "hasValidationError" : false,
                "id" : "pbContainer",
                "rows" : [
                  [
                    {
                      "type" : "component",
                      "dimension" : {
                        "md" : 12,
                        "sm" : 12,
                        "xs" : 12,
                        "lg" : 12
                      },
                      "propertyValues" : {
                        "labelHidden" : {
                          "type" : "constant",
                          "value" : false
                        },
                        "hidden" : {
                          "type" : "constant",
                          "value" : false
                        },
                        "cssClasses" : {
                          "type" : "constant",
                          "value" : ""
                        },
                        "disabled" : {
                          "type" : "constant",
                          "value" : false
                        },
                        "label" : {
                          "type" : "interpolation",
                          "value" : "Recommend"
                        },
                        "dimension" : {
                          "type" : "constant",
                          "value" : 12
                        },
                        "value" : {
                          "type" : "variable",
                          "value" : "$item.recommendation"
                        },
                        "required" : {
                          "type" : "constant",
                          "value" : false
                        }
                      },
                      "reference" : "72a1c9a8-c799-4e01-b6b0-bc549fb32233",
                      "hasValidationError" : false,
                      "id" : "pbCheckbox",
                      "description" : ""
                    }
                  ],
                  [
                    {
                      "type" : "component",
                      "dimension" : {
                        "md" : 12,
                        "sm" : 12,
                        "xs" : 12,
                        "lg" : 12
                      },
                      "propertyValues" : {
                        "labelHidden" : {
                          "type" : "constant",
                          "value" : false
                        },
                        "hidden" : {
                          "type" : "constant",
                          "value" : false
                        },
                        "labelPosition" : {
                          "type" : "constant",
                          "value" : "top"
                        },
                        "cssClasses" : {
                          "type" : "constant",
                          "value" : ""
                        },
                        "labelWidth" : {
                          "type" : "constant",
                          "value" : 1
                        },
                        "readOnly" : {
                          "type" : "constant",
                          "value" : false
                        },
                        "label" : {
                          "type" : "interpolation",
                          "value" : "Grade"
                        },
                        "placeholder" : {
                          "type" : "constant"
                        },
                        "type" : {
                          "type" : "constant",
                          "value" : "number"
                        },
                        "dimension" : {
                          "type" : "constant",
                          "value" : 12
                        },
                        "value" : {
                          "type" : "variable",
                          "value" : "$item.grade"
                        },
                        "required" : {
                          "type" : "constant",
                          "value" : true
                        },
                        "minLength" : {
                          "type" : "constant",
                          "value" : ""
                        },
                        "maxLength" : {
                          "type" : "constant",
                          "value" : ""
                        },
                        "min" : {
                          "type" : "constant",
                          "value" : 1
                        },
                        "max" : {
                          "type" : "constant",
                          "value" : 5
                        },
                        "step" : {
                          "type" : "constant",
                          "value" : 1
                        }
                      },
                      "reference" : "d83bed2d-0a1e-4087-8126-5bd41c1b3350",
                      "hasValidationError" : false,
                      "id" : "pbInput",
                      "description" : ""
                    }
                  ],
                  [
                    {
                      "type" : "component",
                      "dimension" : {
                        "md" : 12,
                        "sm" : 12,
                        "xs" : 12,
                        "lg" : 12
                      },
                      "propertyValues" : {
                        "labelHidden" : {
                          "type" : "constant",
                          "value" : false
                        },
                        "hidden" : {
                          "type" : "constant",
                          "value" : false
                        },
                        "labelPosition" : {
                          "type" : "constant",
                          "value" : "top"
                        },
                        "cssClasses" : {
                          "type" : "constant",
                          "value" : ""
                        },
                        "labelWidth" : {
                          "type" : "constant",
                          "value" : 1
                        },
                        "readOnly" : {
                          "type" : "constant",
                          "value" : false
                        },
                        "label" : {
                          "type" : "interpolation",
                          "value" : "Description"
                        },
                        "placeholder" : {
                          "type" : "constant"
                        },
                        "type" : {
                          "type" : "constant",
                          "value" : "text"
                        },
                        "dimension" : {
                          "type" : "constant",
                          "value" : 12
                        },
                        "value" : {
                          "type" : "variable",
                          "value" : "$item.description"
                        },
                        "required" : {
                          "type" : "constant",
                          "value" : true
                        },
                        "minLength" : {
                          "type" : "constant",
                          "value" : ""
                        },
                        "maxLength" : {
                          "type" : "constant",
                          "value" : ""
                        },
                        "min" : {
                          "type" : "constant"
                        },
                        "max" : {
                          "type" : "constant"
                        },
                        "step" : {
                          "type" : "constant",
                          "value" : 1
                        }
                      },
                      "reference" : "9c3687a9-a896-45d9-80e5-07c3bfea770d",
                      "hasValidationError" : false,
                      "id" : "pbInput",
                      "description" : ""
                    }
                  ]
                ]
              }
            ],
            [
              {
                "type" : "component",
                "dimension" : {
                  "md" : 12,
                  "sm" : 12,
                  "xs" : 12,
                  "lg" : 12
                },
                "propertyValues" : {
                  "removeItem" : {
                    "type" : "variable"
                  },
                  "hidden" : {
                    "type" : "expression",
                    "value" : "interviewResults.length == 1"
                  },
                  "cssClasses" : {
                    "type" : "constant",
                    "value" : ""
                  },
                  "buttonStyle" : {
                    "type" : "constant",
                    "value" : "primary"
                  },
                  "label" : {
                    "type" : "interpolation",
                    "value" : "<span class=\"glyphicon glyphicon-plus\"></span> Add Interview Result"
                  },
                  "dataToSend" : {
                    "type" : "expression"
                  },
                  "labelHidden" : {
                    "type" : "constant",
                    "value" : false
                  },
                  "collectionPosition" : {
                    "type" : "constant"
                  },
                  "targetUrlOnSuccess" : {
                    "type" : "interpolation"
                  },
                  "action" : {
                    "type" : "constant",
                    "value" : "Add to collection"
                  },
                  "collectionToModify" : {
                    "type" : "variable",
                    "value" : "interviewResults"
                  },
                  "valueToAdd" : {
                    "type" : "expression",
                    "value" : "{\r\n  \"persistenceId_string\" : \"\",\r\n  \"recommendation\" : false,\r\n  \"grade\" : 0,\r\n  \"description\" : \"\"\r\n}"
                  },
                  "disabled" : {
                    "type" : "constant",
                    "value" : false
                  },
                  "alignment" : {
                    "type" : "constant",
                    "value" : "left"
                  },
                  "dimension" : {
                    "type" : "constant",
                    "value" : 12
                  },
                  "assign" : {
                    "type" : "constant",
                    "value" : false
                  },
                  "url" : {
                    "type" : "interpolation"
                  },
                  "responseStatusCode" : {
                    "type" : "variable"
                  },
                  "dataFromSuccess" : {
                    "type" : "variable"
                  },
                  "closeOnSuccess" : {
                    "type" : "constant",
                    "value" : false
                  },
                  "dataFromError" : {
                    "type" : "variable"
                  },
                  "modalId" : {
                    "type" : "constant",
                    "value" : ""
                  }
                },
                "reference" : "eb729140-4db4-4f5c-a8d4-b15032320d93",
                "hasValidationError" : false,
                "id" : "pbButton",
                "description" : ""
              }
            ],
            [
              {
                "type" : "component",
                "dimension" : {
                  "md" : 12,
                  "sm" : 12,
                  "xs" : 12,
                  "lg" : 12
                },
                "propertyValues" : {
                  "removeItem" : {
                    "type" : "variable"
                  },
                  "hidden" : {
                    "type" : "constant",
                    "value" : false
                  },
                  "cssClasses" : {
                    "type" : "constant",
                    "value" : ""
                  },
                  "buttonStyle" : {
                    "type" : "constant",
                    "value" : "primary"
                  },
                  "label" : {
                    "type" : "interpolation",
                    "value" : "Confirm"
                  },
                  "dataToSend" : {
                    "type" : "expression",
                    "value" : "formOutput"
                  },
                  "dataFromError" : {
                    "type" : "variable",
                    "value" : "formOutput._submitError"
                  },
                  "labelHidden" : {
                    "type" : "constant",
                    "value" : false
                  },
                  "collectionPosition" : {
                    "type" : "constant"
                  },
                  "targetUrlOnSuccess" : {
                    "type" : "interpolation",
                    "value" : "/bonita"
                  },
                  "action" : {
                    "type" : "constant",
                    "value" : "Submit task"
                  },
                  "collectionToModify" : {
                    "type" : "variable"
                  },
                  "valueToAdd" : {
                    "type" : "expression"
                  },
                  "disabled" : {
                    "type" : "expression",
                    "value" : "$form.$invalid && interviewResults.length != 1"
                  },
                  "alignment" : {
                    "type" : "constant",
                    "value" : "center"
                  },
                  "dimension" : {
                    "type" : "constant",
                    "value" : 12
                  },
                  "assign" : {
                    "type" : "constant",
                    "value" : false
                  },
                  "url" : {
                    "type" : "interpolation"
                  },
                  "responseStatusCode" : {
                    "type" : "variable",
                    "value" : ""
                  },
                  "dataFromSuccess" : {
                    "type" : "variable",
                    "value" : ""
                  },
                  "closeOnSuccess" : {
                    "type" : "constant",
                    "value" : false
                  },
                  "modalId" : {
                    "type" : "constant",
                    "value" : ""
                  }
                },
                "reference" : "f659af92-d14d-44db-a9a0-44d34d6499b7",
                "hasValidationError" : false,
                "id" : "pbButton",
                "description" : ""
              }
            ],
            [
              {
                "type" : "component",
                "dimension" : {
                  "md" : 12,
                  "sm" : 12,
                  "xs" : 12,
                  "lg" : 12
                },
                "propertyValues" : {
                  "allowHTML" : {
                    "type" : "constant",
                    "value" : true
                  },
                  "allowHtml" : {
                    "type" : "constant",
                    "value" : true
                  },
                  "labelHidden" : {
                    "type" : "constant",
                    "value" : true
                  },
                  "hidden" : {
                    "type" : "expression",
                    "value" : "!formOutput._submitError.message"
                  },
                  "cssClasses" : {
                    "type" : "constant",
                    "value" : "alert alert-danger col-lg-6 col-lg-offset-3"
                  },
                  "label" : {
                    "type" : "interpolation"
                  },
                  "text" : {
                    "type" : "interpolation",
                    "value" : "<strong>Debug message</strong>\n<br/>\n{{formOutput._submitError.message}}\n{{submit_errors_list}}"
                  },
                  "alignment" : {
                    "type" : "constant",
                    "value" : "left"
                  },
                  "dimension" : {
                    "type" : "constant",
                    "value" : 12
                  },
                  "labelPosition" : {
                    "type" : "constant",
                    "value" : "top"
                  },
                  "labelWidth" : {
                    "type" : "constant",
                    "value" : 4
                  }
                },
                "reference" : "3edcd4ad-a284-43f7-9439-d57ed9208f7e",
                "hasValidationError" : false,
                "id" : "pbText",
                "description" : ""
              }
            ]
          ]
        }
      }
    ]
  ],
  "assets" : [
    {
      "id" : "343b59e7-d4a8-4288-8da5-be7b53860dd6",
      "name" : "localization.json",
      "type" : "json",
      "order" : 0,
      "external" : false
    },
    {
      "id" : "38454b18-3c89-449a-9660-c527a4b48a8b",
      "name" : "style.css",
      "type" : "css",
      "order" : 0,
      "external" : false
    }
  ],
  "inactiveAssets" : [ ],
  "variables" : {
    "task" : {
      "type" : "url",
      "value" : [
        "../API/bpm/userTask/{{taskId}}"
      ],
      "exposed" : false
    },
    "interviewResult_query" : {
      "type" : "url",
      "value" : [
        "../API/bdm/businessData/com.company.model.jobapplication.InterviewResult?q=find&p=0&c=99"
      ],
      "exposed" : false
    },
    "interviewResults" : {
      "type" : "url",
      "value" : [
        "../{{context.interviewResults_ref.link}}"
      ],
      "exposed" : false
    },
    "submit_errors_list" : {
      "type" : "expression",
      "value" : [
        "if($data.formOutput && $data.formOutput._submitError && $data.formOutput._submitError.explanations){",
        "\tconst liElements = $data.formOutput._submitError.explanations",
        "\t\t.filter(cause => cause !== null)",
        "\t\t.map(cause => \"<li>\" + cause + \"</li>\")",
        "\t\t.join('');",
        "\tif(liElements){",
        "\t\treturn \"<ul>\" + liElements + \"</ul>\";",
        "\t}",
        "}"
      ],
      "exposed" : false
    },
    "formOutput" : {
      "type" : "expression",
      "value" : [
        "if( $data.jobApplication && $data.jobApplication_potentialInterviewTerms && $data.jobApplication_choosenInterviewTerm && $data.jobApplication_interviewResults && $data.interviewResults ){",
        "\t//attach lazy references variables to parent variables",
        "\t$data.jobApplication.potentialInterviewTerms = $data.jobApplication_potentialInterviewTerms;",
        "\t$data.jobApplication.choosenInterviewTerm = $data.jobApplication_choosenInterviewTerm;",
        "\t$data.jobApplication.interviewResults = $data.jobApplication_interviewResults;",
        "\treturn {",
        "\t\t//map jobApplication variable to expected task contract input",
        "\t\tjobApplicationInput: {",
        "\t\t\tname: $data.jobApplication.name !== undefined ? $data.jobApplication.name : null,",
        "\t\t\tsurname: $data.jobApplication.surname !== undefined ? $data.jobApplication.surname : null,",
        "\t\t\temail: $data.jobApplication.email !== undefined ? $data.jobApplication.email : null,",
        "\t\t\taddress: $data.jobApplication.address !== undefined ? $data.jobApplication.address : null,",
        "\t\t\tgradeOfEducation: $data.jobApplication.gradeOfEducation !== undefined ? $data.jobApplication.gradeOfEducation : null,",
        "\t\t\tcv: $data.jobApplication.cv !== undefined ? $data.jobApplication.cv : null,",
        "\t\t\tletter: $data.jobApplication.letter !== undefined ? $data.jobApplication.letter : null,",
        "\t\t\tchoosenInterviewTerm: $data.jobApplication.choosenInterviewTerm ? {",
        "\t\t\t\tpersistenceId_string: $data.jobApplication.choosenInterviewTerm.persistenceId_string !== undefined ? $data.jobApplication.choosenInterviewTerm.persistenceId_string : null,",
        "\t\t\t\tdateTime: $data.jobApplication.choosenInterviewTerm.dateTime !== undefined ? $data.jobApplication.choosenInterviewTerm.dateTime : null",
        "\t\t\t} : null,",
        "\t\t\tinterviewResults: $data.jobApplication.interviewResults.map( it => ({",
        "\t\t\t\tpersistenceId_string: it.persistenceId_string !== undefined ? it.persistenceId_string : null,",
        "\t\t\t\trecommendation: it.recommendation !== undefined ? it.recommendation : null,",
        "\t\t\t\tgrade: it.grade !== undefined ? it.grade : null,",
        "\t\t\t\tdescription: it.description !== undefined ? it.description : null",
        "\t\t\t}))",
        "\t\t},",
        "\t\t//map interviewResults variable to expected task contract input",
        "\t\tinterviewResultsInput: $data.interviewResults.map( it => ({",
        "\t\t\tpersistenceId_string: it.persistenceId_string !== undefined ? it.persistenceId_string : null,",
        "\t\t\trecommendation: it.recommendation !== undefined ? it.recommendation : null,",
        "\t\t\tgrade: it.grade !== undefined ? it.grade : null,",
        "\t\t\tdescription: it.description !== undefined ? it.description : null,",
        "\t\t\ttype: {",
        "\t\t\t\tname: \"Technical\"",
        "\t\t\t}",
        "\t\t}))",
        "\t}",
        "}"
      ],
      "exposed" : false
    },
    "jobApplication" : {
      "type" : "url",
      "value" : [
        "../{{context.jobApplication_ref.link}}"
      ],
      "exposed" : false
    },
    "context" : {
      "type" : "url",
      "value" : [
        "../API/bpm/userTask/{{taskId}}/context"
      ],
      "exposed" : false
    },
    "jobApplication_choosenInterviewTerm" : {
      "type" : "url",
      "value" : [
        "{{jobApplication|lazyRef:'choosenInterviewTerm'}}"
      ],
      "exposed" : false
    },
    "jobApplication_potentialInterviewTerms" : {
      "type" : "url",
      "value" : [
        "{{jobApplication|lazyRef:'potentialInterviewTerms'}}"
      ],
      "exposed" : false
    },
    "interviewTerm_query" : {
      "type" : "url",
      "value" : [
        "../API/bdm/businessData/com.company.model.jobapplication.InterviewTerm?q=find&p=0&c=99"
      ],
      "exposed" : false
    },
    "taskId" : {
      "type" : "urlparameter",
      "value" : [
        "id"
      ],
      "exposed" : false
    },
    "jobApplication_interviewResults" : {
      "type" : "url",
      "value" : [
        "{{jobApplication|lazyRef:'interviewResults'}}"
      ],
      "exposed" : false
    }
  },
  "hasValidationError" : false,
  "uuid" : "278e5302-09dd-4c72-96ca-0b029ca29211",
  "type" : "form",
  "description" : "Page generated with Bonita UI designer"
}